jupyter_mesh/__init__.py
jupyter_mesh/_version.py
jupyter_mesh/handlers.py
jupyter_mesh/tests/__init__.py
jupyter_mesh/tests/test_handlers.py
jupyter_mesh-0.0.2.data/data/etc/jupyter/jupyter_notebook_config.d/jupyter_mesh.json
jupyter_mesh-0.0.2.data/data/etc/jupyter/jupyter_server_config.d/jupyter_mesh.json
jupyter_mesh-0.0.2.data/data/share/jupyter/labextensions/@datalayer/jupyter-mesh/build_log.json
jupyter_mesh-0.0.2.data/data/share/jupyter/labextensions/@datalayer/jupyter-mesh/package.json
jupyter_mesh-0.0.2.data/data/share/jupyter/labextensions/@datalayer/jupyter-mesh/schemas/@datalayer/jupyter-mesh/package.json.orig
jupyter_mesh-0.0.2.data/data/share/jupyter/labextensions/@datalayer/jupyter-mesh/schemas/@datalayer/jupyter-mesh/plugin.json
jupyter_mesh-0.0.2.data/data/share/jupyter/labextensions/@datalayer/jupyter-mesh/static/design_icons_lib_index_js.528c32c14e2d8f11c905.js
jupyter_mesh-0.0.2.data/data/share/jupyter/labextensions/@datalayer/jupyter-mesh/static/design_icons_lib_index_js.528c32c14e2d8f11c905.js.map
jupyter_mesh-0.0.2.data/data/share/jupyter/labextensions/@datalayer/jupyter-mesh/static/lib_index_js.06586fce3f21cc1b9d95.js
jupyter_mesh-0.0.2.data/data/share/jupyter/labextensions/@datalayer/jupyter-mesh/static/lib_index_js.06586fce3f21cc1b9d95.js.map
jupyter_mesh-0.0.2.data/data/share/jupyter/labextensions/@datalayer/jupyter-mesh/static/node_modules_object-assign_index_js.30e70a5bbeb24c2c80ab.js
jupyter_mesh-0.0.2.data/data/share/jupyter/labextensions/@datalayer/jupyter-mesh/static/node_modules_object-assign_index_js.30e70a5bbeb24c2c80ab.js.map
jupyter_mesh-0.0.2.data/data/share/jupyter/labextensions/@datalayer/jupyter-mesh/static/remoteEntry.9a59427f88b0c802718f.js
jupyter_mesh-0.0.2.data/data/share/jupyter/labextensions/@datalayer/jupyter-mesh/static/remoteEntry.9a59427f88b0c802718f.js.map
jupyter_mesh-0.0.2.data/data/share/jupyter/labextensions/@datalayer/jupyter-mesh/static/style.js
jupyter_mesh-0.0.2.dist-info/METADATA
jupyter_mesh-0.0.2.dist-info/WHEEL
jupyter_mesh-0.0.2.dist-info/licenses/LICENSE
jupyter_mesh-0.0.2.dist-info/RECORD
